autodl/__init__.py
autodl/auto_ingestion/__init__.py
autodl/auto_ingestion/data_converter.py
autodl/auto_ingestion/data_io.py
autodl/auto_ingestion/data_pb2.py
autodl/auto_ingestion/dataset.py
autodl/auto_ingestion/dataset_utils.py
autodl/auto_ingestion/dataset_utils_v2.py
autodl/auto_ingestion/pure_model_run.py
autodl/auto_models/__init__.py
autodl/auto_models/model.py
autodl/auto_models/model_nlp.py
autodl/auto_models/nlp_autodl_config.py
autodl/auto_models/nlp_dataset_convertor.py
autodl/auto_models/at_nlp/__init__.py
autodl/auto_models/at_nlp/evaluator.py
autodl/auto_models/at_nlp/run_model.py
autodl/auto_models/at_nlp/utils.py
autodl/auto_models/at_nlp/data_manager/__init__.py
autodl/auto_models/at_nlp/data_manager/data_sampler.py
autodl/auto_models/at_nlp/data_manager/feature_config.py
autodl/auto_models/at_nlp/data_manager/feature_utils.py
autodl/auto_models/at_nlp/data_manager/preprocess_utils.py
autodl/auto_models/at_nlp/data_manager/sample_config.py
autodl/auto_models/at_nlp/data_manager/sample_utils.py
autodl/auto_models/at_nlp/generators/__init__.py
autodl/auto_models/at_nlp/generators/data_generator.py
autodl/auto_models/at_nlp/generators/ensemble_manager.py
autodl/auto_models/at_nlp/generators/feature_generator.py
autodl/auto_models/at_nlp/generators/model_generator.py
autodl/auto_models/at_nlp/model_lib/__init__.py
autodl/auto_models/at_nlp/model_lib/attention.py
autodl/auto_models/at_nlp/model_lib/cnn_models.py
autodl/auto_models/at_nlp/model_lib/model_utils.py
autodl/auto_models/at_nlp/model_lib/rnn_models.py
autodl/auto_models/at_nlp/model_manager/__init__.py
autodl/auto_models/at_nlp/model_manager/emb_utils.py
autodl/auto_models/at_speech/__init__.py
autodl/auto_models/at_speech/at_speech_config.py
autodl/auto_models/at_speech/at_speech_cons.py
autodl/auto_models/at_speech/model.py
autodl/auto_models/at_speech/backbones/__init__.py
autodl/auto_models/at_speech/backbones/thinresnet34.py
autodl/auto_models/at_speech/backbones/tr34_bb.py
autodl_gpu-0.1.1.dist-info/LICENSE
autodl_gpu-0.1.1.dist-info/METADATA
autodl_gpu-0.1.1.dist-info/WHEEL
autodl_gpu-0.1.1.dist-info/top_level.txt
autodl_gpu-0.1.1.dist-info/RECORD
