Metadata-Version: 2.1
Name: autodl-gpu
Version: 0.1.1
Summary: Automatic Deep Learning, towards fully automated multi-label classification for image, video, text, speech, tabular data.
Home-page: https://github.com/DeepWisdom/AutoDL
Author: DeepWisdom
Author-email: autodl@fuzhi.ai
License: Apache 2.0
Download-URL: https://github.com/DeepWisdom/AutoDL/archive/v1.0.0.tar.gz
Project-URL: Bug Reports, https://github.com/DeepWisdom/AutoDL/issues
Project-URL: Source, https://github.com/DeepWisdom/AutoDL
Keywords: autodl,automl,nas,feature-engineering,model-selection,full-automl,artificial-intelligence,lightgbm,resnet,pytorch,tensorflow,python,autodl-challenge,ai,deeplearning,data-science,machine-learning,big-data,multi-label,automated-machine-learning
Platform: UNKNOWN
Classifier: Intended Audience :: Developers
Classifier: Intended Audience :: Education
Classifier: Intended Audience :: Science/Research
Classifier: License :: OSI Approved :: Apache Software License
Classifier: Programming Language :: Python :: 3.6
Classifier: Programming Language :: Python :: 3.7
Classifier: Topic :: Software Development :: Libraries
Requires-Python: >=3.6
Requires-Dist: numpy (==1.16.2)
Requires-Dist: pandas (==0.24.2)
Requires-Dist: tensorflow-gpu (==1.15.0)
Requires-Dist: jupyter (==1.0.0)
Requires-Dist: seaborn (==0.9.0)
Requires-Dist: scipy (==1.2.1)
Requires-Dist: matplotlib (==3.0.3)
Requires-Dist: scikit-learn (==0.20.3)
Requires-Dist: pyyaml (==5.1.1)
Requires-Dist: psutil (==5.6.6)
Requires-Dist: h5py (==2.9.0)
Requires-Dist: keras (==2.2.4)
Requires-Dist: playsound (==1.2.2)
Requires-Dist: librosa (==0.7.1)
Requires-Dist: protobuf (==3.7.1)
Requires-Dist: xgboost (==0.90)
Requires-Dist: lightgbm (==2.2.3)
Requires-Dist: torch (==1.3.1)
Requires-Dist: torchvision (==0.4.2)
Requires-Dist: jieba (==0.39)
Requires-Dist: nltk (==3.4.5)
Requires-Dist: spacy (==2.1.6)
Requires-Dist: gensim (==3.8.0)
Requires-Dist: polyglot (==16.7.4)
Requires-Dist: hyperopt (==0.2.3)
Requires-Dist: catboost (==0.21)
Requires-Dist: fastai
Requires-Dist: kapre (==0.1.4)
Requires-Dist: keras-radam
Provides-Extra: tests
Requires-Dist: pytest (>=4.4.0) ; extra == 'tests'
Requires-Dist: flake8 ; extra == 'tests'
Requires-Dist: isort ; extra == 'tests'
Requires-Dist: pytest-xdist ; extra == 'tests'
Requires-Dist: pytest-cov ; extra == 'tests'
Requires-Dist: coverage ; extra == 'tests'
Requires-Dist: typeguard (<3,>=2) ; extra == 'tests'
Requires-Dist: typedapi (<0.3,>=0.2) ; extra == 'tests'
